{"classname":"OWLClass_afcef9b0_e4e8_4ff5_994a_b48fc51aeb63","label":"Hospital Administration","description":null,"subclassname":"","subclasslabel":"","subclassdescription":null,"parentclassname":"MeSH","parentclasslabel":"Medical Subject Headings (MeSH)","slug":"medical-subject-headings-mesh-hospital-administration","equalentCollections":[],"topicInsightsDetails":[{"Product":0,"Solution":0,"Service":0,"News":0,"Events":0}],"ancestors":["Medical Subject Headings (MeSH)","Health Care Facilities, Manpower, and Services","Health Facilities","Health Facility Administration","Hospital Administration"],"topicInsightsTotal":0}