{"classname":"Speech_Recognition_Software","label":"Speech Recognition Software","description":null,"subclassname":"","subclasslabel":"","subclassdescription":null,"parentclassname":"MeSH","parentclasslabel":"Medical Subject Headings (MeSH)","slug":"medical-subject-headings-mesh-speech-recognition-software","equalentCollections":[],"topicInsightsDetails":[{"Product":0,"Solution":0,"Service":0,"News":0,"Events":0}],"ancestors":["Medical Subject Headings (MeSH)","Information Science","Computing Methodologies","Software","Speech Recognition Software"],"topicInsightsTotal":0}