{"classname":"Command_and_Control_Center_Officers","label":"Command and Control Center Officers","description":null,"subclassname":"","subclasslabel":"","subclassdescription":null,"parentclassname":"Standard_Occupational_Classification_(SOC)","parentclasslabel":"Standard Occupational Classification (SOC)","slug":"standard-occupational-classification-soc-command-and-control-center-officers","equalentCollections":[],"topicInsightsDetails":[{"Product":0,"Solution":0,"Service":0,"News":0,"Events":0}],"ancestors":["Standard Occupational Classification (SOC)","Military Specific Occupations","Military Officer Special and Tactical Operations Leaders","Command and Control Center Officers"],"topicInsightsTotal":0}