{"classname":"OWLClass_f88735d0_f330_48e3_9e38_5d8fdc1b46ff","label":"Bookkeeping, Accounting, and Auditing Clerks","description":null,"subclassname":"","subclasslabel":"","subclassdescription":null,"parentclassname":"Standard_Occupational_Classification_(SOC)","parentclasslabel":"Standard Occupational Classification (SOC)","slug":"standard-occupational-classification-soc-bookkeeping-accounting-and-auditing-clerks","equalentCollections":[],"topicInsightsDetails":[{"Product":0,"Solution":0,"Service":0,"News":0,"Events":0}],"ancestors":["Standard Occupational Classification (SOC)","Office and Administrative Support Occupations","Financial Clerks","Bookkeeping, Accounting, and Auditing Clerks","Bookkeeping, Accounting, and Auditing Clerks"],"topicInsightsTotal":0}