{"classname":"Demonstrators_and_Product_Promoters","label":"Demonstrators and Product Promoters","description":null,"subclassname":"","subclasslabel":"","subclassdescription":null,"parentclassname":"Standard_Occupational_Classification_(SOC)","parentclasslabel":"Standard Occupational Classification (SOC)","slug":"standard-occupational-classification-soc-demonstrators-and-product-promoters","equalentCollections":[],"topicInsightsDetails":[{"Product":0,"Solution":0,"Service":0,"News":0,"Events":0}],"ancestors":["Standard Occupational Classification (SOC)","Sales and Related Occupations","Other Sales and Related Workers","Models, Demonstrators, and Product Promoters","Demonstrators and Product Promoters"],"topicInsightsTotal":0}